fisher_py/__init__.py
fisher_py/raw_file.py
fisher_py/utils.py
fisher_py/data/__init__.py
fisher_py/data/auto_sampler_information.py
fisher_py/data/common_core_data_object.py
fisher_py/data/device.py
fisher_py/data/error_log_entry.py
fisher_py/data/file_error.py
fisher_py/data/file_header.py
fisher_py/data/file_type.py
fisher_py/data/filter_accurate_mass.py
fisher_py/data/ft_average_options.py
fisher_py/data/peak_options.py
fisher_py/data/raw_file_classification.py
fisher_py/data/raw_file_thread_accessor.py
fisher_py/data/scan_dependent_details.py
fisher_py/data/scan_event.py
fisher_py/data/scan_events.py
fisher_py/data/scan_filter.py
fisher_py/data/sequence_file_writer.py
fisher_py/data/sequence_info.py
fisher_py/data/source_fragmentation_info_valid_type.py
fisher_py/data/tolerance_units.py
fisher_py/data/tray_shape.py
fisher_py/data/business/__init__.py
fisher_py/data/business/barcode_status_type.py
fisher_py/data/business/bracket_type.py
fisher_py/data/business/cached_scan_provider.py
fisher_py/data/business/centroid_stream.py
fisher_py/data/business/chromatogram_signal_cls.py
fisher_py/data/business/chromatogram_trace_settings.py
fisher_py/data/business/data_units.py
fisher_py/data/business/generic_data_types.py
fisher_py/data/business/header_item.py
fisher_py/data/business/instrument_data.py
fisher_py/data/business/instrument_selection.py
fisher_py/data/business/label_peak.py
fisher_py/data/business/log_entry.py
fisher_py/data/business/mass_options.py
fisher_py/data/business/mass_to_frequency_converter.py
fisher_py/data/business/noise_and_baseline.py
fisher_py/data/business/range.py
fisher_py/data/business/range_factory.py
fisher_py/data/business/raw_file_reader_factory.py
fisher_py/data/business/reaction.py
fisher_py/data/business/run_header.py
fisher_py/data/business/sample_information.py
fisher_py/data/business/sample_type.py
fisher_py/data/business/scan.py
fisher_py/data/business/scan_statistics.py
fisher_py/data/business/segmented_scan.py
fisher_py-2.0.2.dist-info/METADATA
fisher_py-2.0.2.dist-info/WHEEL
fisher_py-2.0.2.dist-info/licenses/LICENSE
fisher_py-2.0.2.dist-info/RECORD
