Metadata-Version: 2.4
Name: fisher_py
Version: 2.0.2
Summary: This python module allows to extract data from the RAW-file-format produces by devices from Thermo Fisher Scientific.
Project-URL: Homepage, https://github.com/ethz-institute-of-microbiology/fisher_py
Project-URL: Issues, https://github.com/ethz-institute-of-microbiology/fisher_py/issues
Author-email: Dominik Werner <dominik.werner@live.com>
License-File: LICENSE
Classifier: License :: OSI Approved :: MIT License
Classifier: Operating System :: OS Independent
Classifier: Programming Language :: Python :: 3
Requires-Python: >=3.9
Requires-Dist: numpy>=1.17.0
Requires-Dist: pythonnet>=2.5.1
